[
    {
        "name1": "田畑 良太",
        "degree1": "60: 六段",
        "profile1": "平成２８年７月１７日大会優勝<br/>平成２８年１０月３０日大会優勝"
    },
    {
        "name1": "中村 恭",
        "degree1": "50: 五段",
        "profile1": ""
    },
    {
        "name1": "亀田 雪丸",
        "degree1": "50: 五段",
        "profile1": "社団戦メンバー<br/>平成２８年８月２１日大会優勝<br/>平成２９年１月２２日大会優勝<br/>平成２９年７月１６日大会優勝"
    },
    {
        "name1": "中治 一郎",
        "degree1": "50: 五段",
        "profile1": ""
    },
    {
        "name1": "大田 博朗",
        "degree1": "50: 五段",
        "profile1": "平成２８年８月２１日大会優勝<br/>平成２８年１１月２７日大会優勝"
    },
    {
        "name1": "伊藤 康晴",
        "degree1": "50: 五段",
        "profile1": "平成２８年５月２２日大会優勝"
    },
    {
        "name1": "古井 丈大",
        "degree1": "50: 五段",
        "profile1": "平成２８年９月２５日大会優勝<br/>平成２９年４月２９日大会優勝<br/>平成２９年５月２７日大会優勝<br/>平成２９年６月１８日大会優勝<br/>平成２９年６月１８日五段昇段"
    },
    {
        "name1": "宮本 誠二",
        "degree1": "45: 赤四段",
        "profile1": "平成２９年３月２６日大会優勝"
    },
    {
        "name1": "伊東 竜太",
        "degree1": "40: 四段",
        "profile1": ""
    },
    {
        "name1": "佐藤 正文",
        "degree1": "40: 四段",
        "profile1": "社団戦メンバー<br/>平成２９年２月２６日大会優勝"
    },
    {
        "name1": "内野 和夫",
        "degree1": "40: 四段",
        "profile1": ""
    },
    {
        "name1": "友沢 友春",
        "degree1": "40: 四段",
        "profile1": ""
    },
    {
        "name1": "平野 一豊",
        "degree1": "40: 四段",
        "profile1": "社団戦メンバー"
    },
    {
        "name1": "松下 和広",
        "degree1": "40: 四段",
        "profile1": ""
    },
    {
        "name1": "田村 真理子",
        "degree1": "30: 三段",
        "profile1": "社団戦メンバー"
    },
    {
        "name1": "橋本 智佳子",
        "degree1": "30: 三段",
        "profile1": ""
    },
    {
        "name1": "中村 孝",
        "degree1": "30: 三段",
        "profile1": ""
    },
    {
        "name1": "塩谷 大暉",
        "degree1": "30: 三段",
        "profile1": ""
    },
    {
        "name1": "杉浦 正樹",
        "degree1": "30: 三段",
        "profile1": "社団戦メンバー<br/>平成２８年６月１９日大会優勝"
    },
    {
        "name1": "河野 日香",
        "degree1": "30: 三段",
        "profile1": "社団戦メンバー"
    },
    {
        "name1": "谷田部 友紀",
        "degree1": "30: 三段",
        "profile1": ""
    },
    {
        "name1": "前田 俊博",
        "degree1": "20: 二段",
        "profile1": "社団戦メンバー"
    },
    {
        "name1": "山本 祐輔",
        "degree1": "20: 二段",
        "profile1": "平成２８年１２月１８日グランドチャンピオン大会優勝"
    },
    {
        "name1": "福園 真也",
        "degree1": "20: 二段",
        "profile1": "社団戦メンバー"
    },
    {
        "name1": "竹内 英明",
        "degree1": "20: 二段",
        "profile1": "社団戦メンバー"
    },
    {
        "name1": "伊藤 瑠希",
        "degree1": "20: 二段",
        "profile1": ""
    },
    {
        "name1": "具志 朝之",
        "degree1": "20: 二段",
        "profile1": "社団戦メンバー"
    },
    {
        "name1": "大田黒 裕",
        "degree1": "20: 二段",
        "profile1": ""
    },
    {
        "name1": "山崎 貴俊",
        "degree1": "20: 三段",
        "profile1": "平成２９年７月１６日五段昇段"
    },
    {
        "name1": "内免 梓",
        "degree1": "20: 二段",
        "profile1": "平成２８年６月１９日大会優勝"
    },
    {
        "name1": "上原 洋",
        "degree1": "00: 指導員",
        "profile1": "社団戦監督"
    },
    {
        "name1": "小池 裕喜",
        "degree1": "00: 先生",
        "profile1": "小金井将棋研究会特別企画 田畑良太試練の一番勝負優勝"
    },
    {
        "name1": "大竹さん",
        "degree1": "20: 二段",
        "profile1": ""
    },
    {
        "name1": "楠本さん",
        "degree1": "30: 三段",
        "profile1": ""
    },
    {
        "name1": "大島さん",
        "degree1": "30: 三段",
        "profile1": ""
    }
]
